CHANGES.txt
MANIFEST.in
README.txt
buildout.cfg
minitage.cfg
setup.cfg
setup.py
src/minitage/__init__.py
src/minitage.recipe.common.egg-info/PKG-INFO
src/minitage.recipe.common.egg-info/SOURCES.txt
src/minitage.recipe.common.egg-info/dependency_links.txt
src/minitage.recipe.common.egg-info/namespace_packages.txt
src/minitage.recipe.common.egg-info/not-zip-safe
src/minitage.recipe.common.egg-info/requires.txt
src/minitage.recipe.common.egg-info/top_level.txt
src/minitage/recipe/__init__.py
src/minitage/recipe/common/__init__.py
src/minitage/recipe/common/common.py
src/minitage/recipe/common/tests/__init__.py
src/minitage/recipe/common/tests/api.txt
src/minitage/recipe/common/tests/shared.txt
src/minitage/recipe/common/tests/test_recipe.py
src/minitage/recipe/common/tests/tests.py